django_deployer/__init__.py
django_deployer/cli.py
django_deployer/client.py
django_deployer/config.py
django_deployer/deployer.py
django_deployer/host.py
django_deployer/logger.py
django_deployer/token.py
django_deployer/utils.py
dj_deployer-1.0.3.dist-info/METADATA
dj_deployer-1.0.3.dist-info/WHEEL
dj_deployer-1.0.3.dist-info/entry_points.txt
dj_deployer-1.0.3.dist-info/top_level.txt
dj_deployer-1.0.3.dist-info/RECORD
